Metadata-Version: 1.1
Name: fucking
Version: 2.1.0
Summary: a python tool which make English word to Chinese using the baidu translate.
Home-page: https://github.com/Yaoxuannn/Python_Tools
Author: justin13
Author-email: justin13wyx@gmail.com
License: UNKNOWN
Keywords: python3 translate terminal
Platform: UNKNOWN
Classifier: Development Status :: 5 - Production/Stable
Classifier: Natural Language :: Chinese (Simplified)
Classifier: Operating System :: OS Independent
Classifier: Programming Language :: Python :: 3 :: Only
Classifier: Topic :: Terminals
